shapxplain/__init__.py
shapxplain/explainers.py
shapxplain/prompts.py
shapxplain/schemas.py
shapxplain/utils.py
shapxplain-0.1.0.dist-info/LICENSE
shapxplain-0.1.0.dist-info/METADATA
shapxplain-0.1.0.dist-info/WHEEL
shapxplain-0.1.0.dist-info/RECORD
