Metadata-Version: 2.1
Name: shapxplain
Version: 0.1.0
Summary: SHAP and LLM-based explanations for model interpretability
Home-page: https://github.com/michaelpearmain/shapxplain
Keywords: machine-learning,interpretability,explainability,shap,llm
Author: Mike Pearmain
Author-email: michael.pearmain@gmail.com
Requires-Python: >=3.12,<4.0
Classifier: Development Status :: 4 - Beta
Classifier: Intended Audience :: Developers
Classifier: Intended Audience :: Science/Research
Classifier: License :: OSI Approved :: MIT License
Classifier: Programming Language :: Python :: 3
Classifier: Programming Language :: Python :: 3.12
Classifier: Topic :: Scientific/Engineering :: Artificial Intelligence
Requires-Dist: numba (==0.60.0)
Requires-Dist: openai (>=1.60.0,<2.0.0)
Requires-Dist: plotly (>=5.24.1,<6.0.0)
Requires-Dist: pydantic-ai (>=0.0.19,<0.0.20)
Requires-Dist: python-dotenv (>=1.0.1,<2.0.0)
Requires-Dist: scikit-learn (>=1.6.1,<2.0.0)
Requires-Dist: shap (>=0.46.0,<0.47.0)
Project-URL: Documentation, https://shapxplain.readthedocs.io
Project-URL: Repository, https://github.com/michaelpearmain/shapxplain
